htmlgenerator/__init__.py
htmlgenerator/base.py
htmlgenerator/htmltags.py
htmlgenerator/lazy.py
htmlgenerator/py.typed
htmlgenerator/safestring.py
htmlgenerator/contrib/__init__.py
htmlgenerator/contrib/convertfromhtml.py
tests/__init__.py
tests/test_parsing.py
tests/test_rendering.py
htmlgenerator-1.2.32.dist-info/LICENSE
htmlgenerator-1.2.32.dist-info/METADATA
htmlgenerator-1.2.32.dist-info/WHEEL
htmlgenerator-1.2.32.dist-info/entry_points.txt
htmlgenerator-1.2.32.dist-info/top_level.txt
htmlgenerator-1.2.32.dist-info/RECORD
