Metadata-Version: 2.1
Name: htmlgenerator
Version: 1.2.32
Summary: Declarative HTML templating system with lazy rendering
Home-page: https://github.com/basxsoftwareassociation/htmlgenerator
Author: basx Software Association
Author-email: sam@basx.dev
License: New BSD License
Classifier: Development Status :: 4 - Beta
Classifier: Environment :: Console
Classifier: Environment :: Web Environment
Classifier: Intended Audience :: Developers
Classifier: License :: OSI Approved :: BSD License
Classifier: Programming Language :: Python
Classifier: Programming Language :: Python :: 3 :: Only
License-File: LICENSE
Provides-Extra: all
Requires-Dist: black; extra == "all"
Requires-Dist: beautifulsoup4; extra == "all"
Requires-Dist: lxml; platform_system != "Windows" and extra == "all"
